paramiko-stubs/METADATA.toml
paramiko-stubs/__init__.pyi
paramiko-stubs/_winapi.pyi
paramiko-stubs/agent.pyi
paramiko-stubs/auth_handler.pyi
paramiko-stubs/auth_strategy.pyi
paramiko-stubs/ber.pyi
paramiko-stubs/buffered_pipe.pyi
paramiko-stubs/channel.pyi
paramiko-stubs/client.pyi
paramiko-stubs/common.pyi
paramiko-stubs/compress.pyi
paramiko-stubs/config.pyi
paramiko-stubs/ecdsakey.pyi
paramiko-stubs/ed25519key.pyi
paramiko-stubs/file.pyi
paramiko-stubs/hostkeys.pyi
paramiko-stubs/kex_curve25519.pyi
paramiko-stubs/kex_ecdh_nist.pyi
paramiko-stubs/kex_gex.pyi
paramiko-stubs/kex_group1.pyi
paramiko-stubs/kex_group14.pyi
paramiko-stubs/kex_group16.pyi
paramiko-stubs/kex_gss.pyi
paramiko-stubs/message.pyi
paramiko-stubs/packet.pyi
paramiko-stubs/pipe.pyi
paramiko-stubs/pkey.pyi
paramiko-stubs/primes.pyi
paramiko-stubs/proxy.pyi
paramiko-stubs/py.typed
paramiko-stubs/rsakey.pyi
paramiko-stubs/server.pyi
paramiko-stubs/sftp.pyi
paramiko-stubs/sftp_attr.pyi
paramiko-stubs/sftp_client.pyi
paramiko-stubs/sftp_file.pyi
paramiko-stubs/sftp_handle.pyi
paramiko-stubs/sftp_server.pyi
paramiko-stubs/sftp_si.pyi
paramiko-stubs/ssh_exception.pyi
paramiko-stubs/ssh_gss.pyi
paramiko-stubs/transport.pyi
paramiko-stubs/util.pyi
paramiko-stubs/win_openssh.pyi
paramiko-stubs/win_pageant.pyi
types_paramiko-4.0.0.20250821.dist-info/licenses/LICENSE
types_paramiko-4.0.0.20250821.dist-info/METADATA
types_paramiko-4.0.0.20250821.dist-info/WHEEL
types_paramiko-4.0.0.20250821.dist-info/top_level.txt
types_paramiko-4.0.0.20250821.dist-info/RECORD
